isimip_qc/__init__.py
isimip_qc/config.py
isimip_qc/exceptions.py
isimip_qc/fixes.py
isimip_qc/main.py
isimip_qc/models.py
isimip_qc/checks/3d.py
isimip_qc/checks/__init__.py
isimip_qc/checks/attributes.py
isimip_qc/checks/dataset.py
isimip_qc/checks/dimensions.py
isimip_qc/checks/experiments.py
isimip_qc/checks/variables/__init__.py
isimip_qc/checks/variables/latlon.py
isimip_qc/checks/variables/time.py
isimip_qc/checks/variables/time_resolution.py
isimip_qc/checks/variables/var.py
isimip_qc/checks/variables/var3d.py
isimip_qc/utils/__init__.py
isimip_qc/utils/datamodel.py
isimip_qc/utils/experiments.py
isimip_qc/utils/files.py
isimip_qc/utils/logging.py
isimip_qc-3.5.dist-info/licenses/LICENSE
isimip_qc-3.5.dist-info/METADATA
isimip_qc-3.5.dist-info/WHEEL
isimip_qc-3.5.dist-info/entry_points.txt
isimip_qc-3.5.dist-info/top_level.txt
isimip_qc-3.5.dist-info/RECORD
