Metadata-Version: 2.4
Name: isimip-qc
Version: 3.5
Summary: A command line tool for the quality control of climate impact data of the ISIMIP project.
Author-email: Matthias Büchner <buechner@pik-potsdam.de>, Jochen Klar <jochen.klar@pik-potsdam.de>
Maintainer-email: Matthias Büchner <buechner@pik-potsdam.de>
License-Expression: MIT
Project-URL: Repository, https://github.com/ISI-MIP/isimip-qc
Project-URL: Issues, https://github.com/ISI-MIP/isimip-qc/issues
Classifier: Operating System :: OS Independent
Classifier: Programming Language :: Python :: 3.8
Classifier: Programming Language :: Python :: 3.9
Classifier: Programming Language :: Python :: 3.10
Classifier: Programming Language :: Python :: 3.11
Requires-Python: >=3.8
License-File: LICENSE
Requires-Dist: colorlog
Requires-Dist: isimip-utils>=1.2
Requires-Dist: jsonschema
Requires-Dist: netCDF4
Requires-Dist: prettytable
Requires-Dist: python-dotenv
Requires-Dist: requests
Provides-Extra: dev
Requires-Dist: build; extra == "dev"
Requires-Dist: pre-commit; extra == "dev"
Requires-Dist: ruff; extra == "dev"
Requires-Dist: twine; extra == "dev"
Dynamic: license-file
